kilroy_module_pytorch_py_sdk/__init__.py
kilroy_module_pytorch_py_sdk/gae.py
kilroy_module_pytorch_py_sdk/generator/__init__.py
kilroy_module_pytorch_py_sdk/generator/generator.py
kilroy_module_pytorch_py_sdk/generator/parameters.py
kilroy_module_pytorch_py_sdk/generator/params.py
kilroy_module_pytorch_py_sdk/generator/state.py
kilroy_module_pytorch_py_sdk/losses/__init__.py
kilroy_module_pytorch_py_sdk/losses/distribution/__init__.py
kilroy_module_pytorch_py_sdk/losses/distribution/jsm.py
kilroy_module_pytorch_py_sdk/losses/distribution/loss.py
kilroy_module_pytorch_py_sdk/losses/policy/__init__.py
kilroy_module_pytorch_py_sdk/losses/policy/loss.py
kilroy_module_pytorch_py_sdk/losses/policy/nll.py
kilroy_module_pytorch_py_sdk/losses/value/__init__.py
kilroy_module_pytorch_py_sdk/losses/value/loss.py
kilroy_module_pytorch_py_sdk/losses/value/mse.py
kilroy_module_pytorch_py_sdk/metrics.py
kilroy_module_pytorch_py_sdk/models/__init__.py
kilroy_module_pytorch_py_sdk/models/abc.py
kilroy_module_pytorch_py_sdk/models/loader.py
kilroy_module_pytorch_py_sdk/models/registry.py
kilroy_module_pytorch_py_sdk/module/__init__.py
kilroy_module_pytorch_py_sdk/module/module.py
kilroy_module_pytorch_py_sdk/module/parameters.py
kilroy_module_pytorch_py_sdk/module/params.py
kilroy_module_pytorch_py_sdk/module/state.py
kilroy_module_pytorch_py_sdk/optimizers/__init__.py
kilroy_module_pytorch_py_sdk/optimizers/adam.py
kilroy_module_pytorch_py_sdk/optimizers/base.py
kilroy_module_pytorch_py_sdk/optimizers/rmsprop.py
kilroy_module_pytorch_py_sdk/optimizers/sgd.py
kilroy_module_pytorch_py_sdk/regularizations/__init__.py
kilroy_module_pytorch_py_sdk/regularizations/policy/__init__.py
kilroy_module_pytorch_py_sdk/regularizations/policy/base.py
kilroy_module_pytorch_py_sdk/regularizations/policy/departure/__init__.py
kilroy_module_pytorch_py_sdk/regularizations/policy/departure/parameters.py
kilroy_module_pytorch_py_sdk/regularizations/policy/departure/params.py
kilroy_module_pytorch_py_sdk-0.8.4.dist-info/LICENSE
kilroy_module_pytorch_py_sdk-0.8.4.dist-info/WHEEL
kilroy_module_pytorch_py_sdk-0.8.4.dist-info/METADATA
kilroy_module_pytorch_py_sdk-0.8.4.dist-info/RECORD
