Metadata-Version: 2.1
Name: kilroy-module-pytorch-py-sdk
Version: 0.8.4
Summary: SDK for kilroy modules using PyTorch 🧰
Home-page: https://github.com/kilroybot/kilroy-module-pytorch-py-sdk
Author: kilroy
Author-email: kilroymail@pm.me
Requires-Python: >=3.10,<4.0
Classifier: License :: OSI Approved :: MIT License
Classifier: Operating System :: OS Independent
Classifier: Programming Language :: Python :: 3
Classifier: Programming Language :: Python :: 3.10
Requires-Dist: kilroy-module-server-py-sdk (>=0.10,<0.11)
Requires-Dist: numpy (>=1,<2)
Requires-Dist: torch (>=1,<2)
Project-URL: Documentation, https://kilroybot.github.io/kilroy-module-pytorch-py-sdk
Project-URL: Repository, https://github.com/kilroybot/kilroy-module-pytorch-py-sdk
